pydosh
