Metadata-Version: 1.0
Name: pydosh
Version: 1.7
Summary: Bank statement transaction manager, written in PyQt
Home-page: http://github.com/innerhippy/pydosh
Author: Will Hall
Author-email: will@innerhippy.com
License: GPLv3
Platform: UNKNOWN
